sqlo/__init__.py
sqlo/builder.py
sqlo/constants.py
sqlo/expressions.py
sqlo/py.typed
sqlo/security.py
sqlo/window.py
sqlo/dialects/base.py
sqlo/dialects/mysql.py
sqlo/query/base.py
sqlo/query/delete.py
sqlo/query/insert.py
sqlo/query/mixins.py
sqlo/query/select.py
sqlo/query/update.py
sqlo-0.2.1.dist-info/METADATA
sqlo-0.2.1.dist-info/WHEEL
sqlo-0.2.1.dist-info/licenses/LICENSE
sqlo-0.2.1.dist-info/RECORD
